shorttext/__init__.py
shorttext/smartload.py
shorttext/classifiers/__init__.py
shorttext/classifiers/bow/__init__.py
shorttext/classifiers/bow/maxent/MaxEntClassification.py
shorttext/classifiers/bow/maxent/__init__.py
shorttext/classifiers/bow/topic/SkLearnClassification.py
shorttext/classifiers/bow/topic/TopicVectorDistanceClassification.py
shorttext/classifiers/bow/topic/__init__.py
shorttext/classifiers/embed/__init__.py
shorttext/classifiers/embed/nnlib/VarNNEmbedVecClassification.py
shorttext/classifiers/embed/nnlib/__init__.py
shorttext/classifiers/embed/nnlib/frameworks.py
shorttext/classifiers/embed/sumvec/SumEmbedVecClassification.py
shorttext/classifiers/embed/sumvec/VarNNSumEmbedVecClassification.py
shorttext/classifiers/embed/sumvec/__init__.py
shorttext/classifiers/embed/sumvec/frameworks.py
shorttext/cli/__init__.py
shorttext/cli/categorization.py
shorttext/cli/wordembedsim.py
shorttext/data/__init__.py
shorttext/data/data_retrieval.py
shorttext/data/shorttext_exampledata.csv
shorttext/generators/__init__.py
shorttext/generators/bow/AutoEncodingTopicModeling.py
shorttext/generators/bow/GensimTopicModeling.py
shorttext/generators/bow/LatentTopicModeling.py
shorttext/generators/bow/__init__.py
shorttext/generators/charbase/__init__.py
shorttext/generators/charbase/char2vec.py
shorttext/generators/seq2seq/__init__.py
shorttext/generators/seq2seq/charbaseS2S.py
shorttext/generators/seq2seq/s2skeras.py
shorttext/metrics/__init__.py
shorttext/metrics/dynprog/__init__.py
shorttext/metrics/dynprog/dldist.py
shorttext/metrics/dynprog/jaccard.py
shorttext/metrics/dynprog/lcp.py
shorttext/metrics/embedfuzzy/__init__.py
shorttext/metrics/embedfuzzy/jaccard.py
shorttext/metrics/wasserstein/__init__.py
shorttext/metrics/wasserstein/wordmoverdist.py
shorttext/spell/__init__.py
shorttext/spell/basespellcorrector.py
shorttext/spell/editor.py
shorttext/spell/norvig.py
shorttext/stack/__init__.py
shorttext/stack/stacking.py
shorttext/utils/__init__.py
shorttext-3.0.0.dist-info/licenses/LICENSE
shorttext-3.0.0.dist-info/METADATA
shorttext-3.0.0.dist-info/WHEEL
shorttext-3.0.0.dist-info/entry_points.txt
shorttext-3.0.0.dist-info/top_level.txt
shorttext-3.0.0.dist-info/RECORD
