Metadata-Version: 2.4
Name: shorttext
Version: 3.0.0
Summary: Short Text Mining
Author-email: Kwan Yuet Stephen Ho <stephenhky@yahoo.com.hk>
License: MIT
Project-URL: Repository, https://github.com/stephenhky/PyShortTextCategorization
Project-URL: Issues, https://github.com/stephenhky/PyShortTextCategorization/issues
Project-URL: Documentation, https://shorttext.readthedocs.io
Keywords: shorttext,natural language processing,text mining
Classifier: Topic :: Scientific/Engineering :: Artificial Intelligence
Classifier: Topic :: Scientific/Engineering :: Mathematics
Classifier: Topic :: Text Processing :: Linguistic
Classifier: Topic :: Software Development :: Libraries :: Python Modules
Classifier: Programming Language :: Python :: 3.9
Classifier: Programming Language :: Python :: 3.10
Classifier: Programming Language :: Python :: 3.11
Classifier: Programming Language :: Python :: 3.12
Classifier: Natural Language :: English
Classifier: License :: OSI Approved :: MIT License
Classifier: Intended Audience :: Developers
Classifier: Intended Audience :: Education
Classifier: Intended Audience :: Information Technology
Classifier: Intended Audience :: Science/Research
Requires-Python: >=3.9
License-File: LICENSE
Requires-Dist: numpy>=1.23.3
Requires-Dist: scipy>=1.12.0
Requires-Dist: joblib>=1.3.0
Requires-Dist: scikit-learn>=1.2.0
Requires-Dist: tensorflow>=2.13.0
Requires-Dist: keras>=2.13.0
Requires-Dist: gensim>=4.0.0
Requires-Dist: pandas>=1.2.0
Requires-Dist: snowballstemmer>=3.0.0
Requires-Dist: numba>=0.57.0
Requires-Dist: deprecation>=2.0.0
Provides-Extra: test
Requires-Dist: unittest2; extra == "test"
Requires-Dist: pytest; extra == "test"
Dynamic: license-file
